LICENSE
README.md
pyproject.toml
setup.py
nagios_config_to_csv.egg-info/PKG-INFO
nagios_config_to_csv.egg-info/SOURCES.txt
nagios_config_to_csv.egg-info/dependency_links.txt
nagios_config_to_csv.egg-info/entry_points.txt
nagios_config_to_csv.egg-info/not-zip-safe
nagios_config_to_csv.egg-info/requires.txt
nagios_config_to_csv.egg-info/top_level.txt
nagiosconfigtocsv/__init__.py
nagiosconfigtocsv/__main_.py