Metadata-Version: 2.1
Name: nagios-config-to-csv
Version: 0.0.1
Summary: Extract Nagios Configs to CSV - Python
Home-page: https://github.com/shriasi/nagiosconfigtocsv
Author: Asiri Hewage, Shrimali Senevirathna
Author-email: Asiri Hewage <foolmashi@gmail.com>, Shrimali Senevirathna <shrimaliasi@gmail.com>
License: GNU General Public License v3 (GPLv3)
Project-URL: Homepage, https://github.com/shriasi/nagiosconfigtocsv
Project-URL: Bug Tracker, https://github.com/shriasi/nagiosconfigtocsv/issues
Classifier: Programming Language :: Python :: 3
Classifier: License :: OSI Approved :: MIT License
Classifier: Operating System :: OS Independent
Requires-Python: >=3.6
License-File: LICENSE
